ocean_web3/__init__.py
ocean_web3/acl.py
ocean_web3/config_parser.py
ocean_web3/constants.py
ocean_web3/consumer.py
ocean_web3/ocean_contracts.py
ocean_web3-0.1.2.dist-info/METADATA
ocean_web3-0.1.2.dist-info/RECORD
ocean_web3-0.1.2.dist-info/WHEEL
ocean_web3-0.1.2.dist-info/top_level.txt
