Metadata-Version: 2.1
Name: ocean-web3
Version: 0.1.2
Summary: 🐳 Ocean/Web3py wrapper.
Home-page: https://github.com/oceanprotocol/ocean-web3
Author: leucothia
Author-email: devops@oceanprotocol.com
License: Apache Software License 2.0
Keywords: ocean-web3
Platform: UNKNOWN
Classifier: Development Status :: 2 - Pre-Alpha
Classifier: Intended Audience :: Developers
Classifier: License :: OSI Approved :: Apache Software License
Classifier: Natural Language :: English
Classifier: Programming Language :: Python :: 3.6
Requires-Dist: keeper-contracts
